quiz_mcp/server.py
quiz_mcp/app/__init__.py
quiz_mcp/app/extensions/__init__.py
quiz_mcp/app/extensions/checkbox.py
quiz_mcp/app/extensions/radio.py
quiz_mcp/app/extensions/textbox.py
quiz_mcp/app/static/app.js
quiz_mcp/app/static/base.html
quiz_mcp/app/static/wrapper.html
mcp_quiz_generator-0.1.1.dist-info/METADATA
mcp_quiz_generator-0.1.1.dist-info/WHEEL
mcp_quiz_generator-0.1.1.dist-info/entry_points.txt
mcp_quiz_generator-0.1.1.dist-info/licenses/LICENSE
mcp_quiz_generator-0.1.1.dist-info/RECORD
