Metadata-Version: 2.4
Name: mcp-quiz-generator
Version: 0.1.1
Summary: A Model Context Protocol server for generating HTML and Word quiz files from Markdown content
Project-URL: Homepage, https://github.com/kkjzio/mcp-quiz-generator
Project-URL: Issues, https://github.com/kkjzio/mcp-quiz-generator/issues
Author-email: kkjz <kouyou.kkjz@gmail.com>
License: MIT
License-File: LICENSE
Classifier: Development Status :: 3 - Alpha
Classifier: Intended Audience :: Developers
Classifier: License :: OSI Approved :: MIT License
Classifier: Programming Language :: Python :: 3
Classifier: Programming Language :: Python :: 3.10
Classifier: Programming Language :: Python :: 3.11
Classifier: Programming Language :: Python :: 3.12
Classifier: Programming Language :: Python :: 3.13
Requires-Python: >=3.10
Requires-Dist: click>=8.0.0
Requires-Dist: jinja2==3.1.2
Requires-Dist: markdown==3.1.1
Requires-Dist: markupsafe==2.1.1
Requires-Dist: mcp>=0.5.0
Requires-Dist: python-docx>=0.8.11
Provides-Extra: dev
Requires-Dist: black>=22.0.0; extra == 'dev'
Requires-Dist: flake8>=5.0.0; extra == 'dev'
Requires-Dist: mypy>=1.0.0; extra == 'dev'
Requires-Dist: pytest-cov>=4.0.0; extra == 'dev'
Requires-Dist: pytest>=7.0.0; extra == 'dev'
